timesched.py
timesched-1.9.dist-info/METADATA
timesched-1.9.dist-info/WHEEL
timesched-1.9.dist-info/top_level.txt
timesched-1.9.dist-info/RECORD
