Metadata-Version: 2.4
Name: timesched
Version: 1.9
Summary: Improved simple time scheduler based on standard sched
Author-email: Mark Blakeney <mark.blakeney@bullet-systems.net>
License-Expression: GPL-3.0-or-later
Project-URL: Homepage, https://github.com/bulletmark/timesched
Keywords: sched,scheduler,timer,periodic,cron,crontab
Classifier: Programming Language :: Python :: 3
Requires-Python: >=3.6
